ice_connect/__init__.py
ice_connect/ice.py
ice_connect/utils.py
ice_connect-0.1.2.dist-info/METADATA
ice_connect-0.1.2.dist-info/WHEEL
ice_connect-0.1.2.dist-info/top_level.txt
ice_connect-0.1.2.dist-info/RECORD
