Metadata-Version: 2.4
Name: ice_connect
Version: 0.1.2
Summary: A Python package for Interactive Connectivity Establishment (RFC 5245) with user-defined STUN servers.
Home-page: https://github.com/yetiman45/ice_connect
Author: Dipin Niroula
Author-email: dipinniroula@hotmail.com
License: MIT
Classifier: Programming Language :: Python :: 3
Classifier: License :: OSI Approved :: MIT License
Classifier: Operating System :: OS Independent
Requires-Python: >=3.6
Requires-Dist: pystun3
Requires-Dist: asyncio
Dynamic: author
Dynamic: author-email
Dynamic: classifier
Dynamic: description
Dynamic: description-content-type
Dynamic: home-page
Dynamic: license
Dynamic: requires-dist
Dynamic: requires-python
Dynamic: summary
